sideload_www_bin_6633d5bdad19ca34f86389bb/__init__.py
sideload_www_bin_6633d5bdad19ca34f86389bb-1.0.0.dist-info/METADATA
sideload_www_bin_6633d5bdad19ca34f86389bb-1.0.0.dist-info/WHEEL
sideload_www_bin_6633d5bdad19ca34f86389bb-1.0.0.dist-info/top_level.txt
sideload_www_bin_6633d5bdad19ca34f86389bb-1.0.0.dist-info/RECORD
