Metadata-Version: 2.1
Name: sideload_www_bin_6633d5bdad19ca34f86389bb
Version: 1.0.0
Summary: Sideloaded package
Author: Null Void
Requires-Python: >=3.8
